[{"Title": "Mr. Robot", "Year": "2015\u2013", "imdbID": "tt4158110", "Type": "series", "Poster": "https://m.media-amazon.com/images/M/MV5BMTYzMDE2MzI4MF5BMl5BanBnXkFtZTgwNTkxODgxOTE@._V1_SX300.jpg"}, {"Title": "Mr. Robot Digital After Show", "Year": "2016\u2013", "imdbID": "tt6137444", "Type": "series", "Poster": "https://m.media-amazon.com/images/M/MV5BZTZmNzI5NjQtYWMzNy00NzdhLWFjYTQtMzU3YTIxZGM4OTZlL2ltYWdlL2ltYWdlXkEyXkFqcGdeQXVyOTE1NzY5OQ@@._V1_SX300.jpg"}, {"Title": "Mr. Robot and His Robot Factory", "Year": "1984", "imdbID": "tt0852731", "Type": "game", "Poster": "N/A"}, {"Title": "Mr. Asahi Beer Robot", "Year": "2010", "imdbID": "tt5256428", "Type": "movie", "Poster": "N/A"}, {"Title": "AfterbuzzTV's Mr. Robot Aftershow", "Year": "2015", "imdbID": "tt5260996", "Type": "movie", "Poster": "N/A"}, {"Title": "Mr. Robot: M4k1ng_0f_Mr_R0b0t.m0v", "Year": "2016", "imdbID": "tt5321406", "Type": "movie", "Poster": "N/A"}]